{"lastModified":1353534177000,"name":"Nerd","realm":"Blackmoore","battlegroup":"Glutsturm / Emberstorm","class":3,"race":4,"gender":0,"level":60,"achievementPoints":12240,"thumbnail":"blackmoore/37/110373-avatar.jpg","calcClass":"Y","stats":{"health":5887,"powerType":"focus","power":100,"str":57,"agi":286,"sta":226,"int":65,"spr":70,"attackPower":574,"rangedAttackPower":879,"pvpResilienceBonus":0.0,"mastery":8.0,"masteryRating":0,"crit":12.377956,"critRating":74,"hitPercent":7.375,"hitRating":59,"haste":0.0,"hasteRating":0,"hasteRatingPercent":0.0,"expertiseRating":0,"spellPower":55,"spellPen":0,"spellCrit":5.292214,"spellCritRating":74,"spellHitPercent":7.375,"spellHitRating":59,"mana5":0.0,"mana5Combat":0.0,"spellHaste":0.0,"spellHasteRating":0,"spellHasteRatingPercent":0.0,"armor":2517,"dodge":16.09469,"dodgeRating":0,"parry":0.0,"parryRating":0,"block":0.0,"blockRating":0,"pvpResilience":40.0,"pvpResilienceRating":0,"mainHandDmgMin":115.0,"mainHandDmgMax":116.0,"mainHandSpeed":2.0,"mainHandDps":57.900005,"mainHandExpertise":0.0,"offHandDmgMin":41.0,"offHandDmgMax":42.0,"offHandSpeed":2.0,"offHandDps":20.750002,"offHandExpertise":0.0,"rangedDmgMin":260.0,"rangedDmgMax":327.0,"rangedSpeed":2.8,"rangedDps":104.87995,"rangedExpertise":0.0,"rangedCrit":12.377956,"rangedCritRating":74,"rangedHitPercent":7.375,"rangedHitRating":59,"rangedHaste":0.0,"rangedHasteRating":0,"rangedHasteRatingPercent":0.0,"pvpPower":0.0,"pvpPowerRating":0,"pvpPowerDamage":0.0,"pvpPowerHealing":0.0}}